pyquerylist
