Metadata-Version: 2.1
Name: pyquerylist
Version: 0.4.0
Summary: List that you can query
Home-page: https://github.com/markmuetz/pyquerylist
Author: Mark Muetzelfeldt
Author-email: mark.muetzelfeldt@reading.ac.uk
Maintainer: Mark Muetzelfeldt
Maintainer-email: mark.muetzelfeldt@reading.ac.uk
License: LICENSE
Project-URL: Documentation, https://markmuetz.github.io/pyquerylist/
Project-URL: Bug Tracker, https://github.com/markmuetz/pyquerylist/issues
Platform: UNKNOWN
Classifier: Environment :: Console
Classifier: Natural Language :: English
Classifier: Operating System :: POSIX :: Linux
Classifier: Programming Language :: Python :: 3.10
Classifier: Development Status :: 4 - Beta
Requires-Python: >=3.8
Provides-Extra: testing
License-File: LICENCE
